<contest-event id="24377">
  <event-date date="2013-10-6">Oct. 6, 2013<event-date>
  <event-date-resolution>D</event-date-resolution>
  <name>Bolsover Entertainment Contest (Unregistered Section)</name>
  <contest id="513">
    <name>Bolsover Entertainment Contest (Unregistered Section)</name>
    <order>60</order>
    <contest-type id="2">Entertainments Contest</contest-type>
    <group id="81">Bolsover Entertainment Contest</group>
    <slug>bolsover-entertainment-contest-unregistered-sectio</slug>
    
    <notes></notes>
    
    
  </contest>
  <contest-type-override id="2">Entertainments Contest</contest-type-override>
  <test-piece>
    
  </test-piece>

  <venue id="1515">Heritage High School, Boughton Lane, Clowne, Derbyshire, England, UK</venue>
  <notes>If anyone from the competing Bands could kindly forward details of the pieces that were played Title, Composer/Arranger - Soloist details and any relevant info I will gladly add to the site, for future reference</notes>

  <created>Oct. 7, 2013, 10:59 a.m.</created>
  <last-modified>Oct. 9, 2013, 11:46 p.m.</last-modified>

  <results>
    
    <result id="177952">
      <result code="1">1</result>
      <band id="3485">Loxley Silver Band</band>
      <conductor id="300614">Lee Dunkley</conductor>
    </result>
    
    <result id="177953">
      <result code="2">2</result>
      <band id="873">City of Lincoln Band</band>
      <conductor id="311782">Robert Wilson</conductor>
    </result>
    
  </results>
</contest-event>
