<contest-event id="40933">
  <event-date date="1923-9-1">Sept. 1, 1923<event-date>
  <event-date-resolution>D</event-date-resolution>
  <name>South Wales &amp; Monmouthshire Brass Band Association (D Section)</name>
  <contest id="3750">
    <name>South Wales &amp; Monmouthshire Brass Band Association (D Section)</name>
    <order>40</order>
    <contest-type id="12">Test Piece Contest</contest-type>
    <group id="95">South Wales &amp; Monmouthshire Brass Band Association</group>
    <slug>south-wales-monmouthshire-brass-band-ass-3750</slug>
    
    <notes>None</notes>
    
    
  </contest>
  
  <test-piece>
    <test-piece id="1089">Country Life</test-piece>
  </test-piece>

  <venue id="2465">Ystrad Mynach, Caerphilly, Wales, UK</venue>
  <notes>Prizes - 1st £5 and cup, 2nd £3, 3rd £1.
March contest - 1st Troedyrhiw Town, 2nd Cwm Town.
8 bands competed.</notes>

  <created>Oct. 24, 2018, 12:05 p.m.</created>
  <last-modified>Oct. 24, 2018, 1:10 p.m.</last-modified>

  <results>
    
    <result id="297194">
      <result code="1">1</result>
      <band id="4618">Troedyrhiw Silver</band>
      <conductor id="311645">Joseph Williams</conductor>
    </result>
    
    <result id="297195">
      <result code="2">2</result>
      <band id="4790">Pontycymer</band>
      <conductor id="304904">William Layman</conductor>
    </result>
    
    <result id="297196">
      <result code="3">3</result>
      <band id="793">Cwm Town Band</band>
      <conductor id="307754">J. Probert</conductor>
    </result>
    
    <result id="297201">
      <result code="">Unknown Result</result>
      <band id="10967">Mardy</band>
      <conductor id="310730">Unknown</conductor>
    </result>
    
    <result id="297198">
      <result code="">Unknown Result</result>
      <band id="7623">Nelson Temperance</band>
      <conductor id="310730">Unknown</conductor>
    </result>
    
    <result id="297199">
      <result code="">Unknown Result</result>
      <band id="8215">Penrhiwceiber</band>
      <conductor id="310730">Unknown</conductor>
    </result>
    
    <result id="297200">
      <result code="">Unknown Result</result>
      <band id="4618">Troedyrhiw Silver</band>
      <conductor id="310730">Unknown</conductor>
    </result>
    
    <result id="297197">
      <result code="">Unknown Result</result>
      <band id="9593">Ynysybwl</band>
      <conductor id="310730">Unknown</conductor>
    </result>
    
  </results>
</contest-event>
