<contest-event id="30588">
  <event-date date="1974-9-14">Sept. 14, 1974<event-date>
  <event-date-resolution>D</event-date-resolution>
  <name>Cwmaman Festival Contest (Class B)</name>
  <contest id="4131">
    <name>Cwmaman Festival Contest (Class B)</name>
    <order>0</order>
    <contest-type id="9">Own Choice Test Piece Contest</contest-type>
    <group id=""></group>
    <slug>cwmaman-festival-contest-class-b</slug>
    
    <notes>None</notes>
    
    
  </contest>
  
  <test-piece>
    
  </test-piece>

  <venue id="3341">Cwmaman Institute, Cwmaman, Rhondda Cynon Taf, Wales, UK</venue>
  <notes></notes>

  <created>Dec. 11, 2014, 10:06 a.m.</created>
  <last-modified>Dec. 11, 2014, 10:06 a.m.</last-modified>

  <results>
    
    <result id="216251">
      <result code="1">1</result>
      <band id="65">Cwmaman Institute Silver (Tower Colliery) Band</band>
      <conductor id="310730">Unknown</conductor>
    </result>
    
    <result id="216252">
      <result code="2">2</result>
      <band id="344">Llwydcoed Band</band>
      <conductor id="310730">Unknown</conductor>
    </result>
    
    <result id="216253">
      <result code="3">3</result>
      <band id="285">Tongwynlais Temperance Band</band>
      <conductor id="310730">Unknown</conductor>
    </result>
    
  </results>
</contest-event>
