<contest-event id="17301">
  <event-date date="1946-9-7">Sept. 7, 1946<event-date>
  <event-date-resolution>D</event-date-resolution>
  <name>Nanpean Contest (Section 2)</name>
  <contest id="3737">
    <name>Nanpean Contest (Section 2)</name>
    <order>0</order>
    <contest-type id="12">Test Piece Contest</contest-type>
    <group id=""></group>
    <slug>nanpean-contest-section-2</slug>
    
    <notes>None</notes>
    
    
  </contest>
  
  <test-piece>
    <test-piece id="1938">Emilia</test-piece>
  </test-piece>

  <venue id="2853">Old Pound, Nanpean, Cornwall</venue>
  <notes>March contest  1st Newlyn, 2nd Stenalees, 3rd Indian Queens, 4th Truro.
Hymn tune 1st Indian Queens, 2nd Stenalees, 3rd Newlyn, 4th Truro.
Prizes - 1st £15, 2nd £12, 3rd £9.</notes>

  <created>Dec. 24, 2012, 11:44 a.m.</created>
  <last-modified>Feb. 11, 2019, 10 a.m.</last-modified>

  <results>
    
    <result id="131214">
      <result code="1">1</result>
      <band id="6463">Stenalees Silver Band</band>
      <conductor id="297359">Charles Harry Baker</conductor>
    </result>
    
    <result id="131215">
      <result code="2">2</result>
      <band id="1774">St Newlyn East</band>
      <conductor id="299139">George Cave</conductor>
    </result>
    
    <result id="131216">
      <result code="3">3</result>
      <band id="4496">Truro City</band>
      <conductor id="300023">E. Cuttance</conductor>
    </result>
    
    <result id="131218">
      <result code="4">4</result>
      <band id="254">Bodmin Town Band</band>
      <conductor id="305192">W. T. Lobb</conductor>
    </result>
    
    <result id="131217">
      <result code="">Unknown Result</result>
      <band id="1777">Indian Queens Silver</band>
      <conductor id="304625">Ford Knight</conductor>
    </result>
    
  </results>
</contest-event>
