<contest-event id="25670">
  <event-date date="1933-10-28">Oct. 28, 1933<event-date>
  <event-date-resolution>D</event-date-resolution>
  <name>Atherton Contest</name>
  <contest id="2071">
    <name>Atherton Contest</name>
    <order>0</order>
    <contest-type id="12">Test Piece Contest</contest-type>
    <group id=""></group>
    <slug>atherton-contest</slug>
    
    <notes>None</notes>
    
    
  </contest>
  
  <test-piece>
    <test-piece id="1091">Happy Memories</test-piece>
  </test-piece>

  <venue id="4200">Volunteer Drill Hall, Atherton, Lancashire</venue>
  <notes>Prizes - 1st £10 and cup, 2nd £6, 3rd £4, 4th £2.
  26 bands competed.</notes>

  <created>Dec. 20, 2013, 2:32 p.m.</created>
  <last-modified>April 24, 2018, 12:50 p.m.</last-modified>

  <results>
    
    <result id="185900">
      <result code="1">1</result>
      <band id="388">Bolton (Hoover) Band</band>
      <conductor id="303601">John W. Hughes</conductor>
    </result>
    
    <result id="185901">
      <result code="2">2</result>
      <band id="207">Stalybridge Old Band</band>
      <conductor id="309360">Frank Smith</conductor>
    </result>
    
    <result id="185902">
      <result code="3">3</result>
      <band id="3214">Hurst Village</band>
      <conductor id="299692">Robert Cooper</conductor>
    </result>
    
    <result id="185903">
      <result code="4">4</result>
      <band id="3826">Eccleston Subscription</band>
      <conductor id="297485">T. C. Barlow</conductor>
    </result>
    
    <result id="185904">
      <result code="5">5</result>
      <band id="3313">Earlestown Viaduct</band>
      <conductor id="304174">C. S. Jones</conductor>
    </result>
    
    <result id="280561">
      <result code="">Unknown Result</result>
      <band id="16372">Atherton Temperance</band>
      <conductor id="310730">Unknown</conductor>
    </result>
    
    <result id="185908">
      <result code="">Unknown Result</result>
      <band id="1499">Bedford (Leigh) Band</band>
      <conductor id="310730">Unknown</conductor>
    </result>
    
    <result id="185906">
      <result code="">Unknown Result</result>
      <band id="4353">Bolton Temperance</band>
      <conductor id="310730">Unknown</conductor>
    </result>
    
    <result id="185920">
      <result code="">Unknown Result</result>
      <band id="142">Clifton and Lightcliffe Band</band>
      <conductor id="310730">Unknown</conductor>
    </result>
    
    <result id="185910">
      <result code="">Unknown Result</result>
      <band id="2583">Clock Face Colliery Band</band>
      <conductor id="310730">Unknown</conductor>
    </result>
    
    <result id="185912">
      <result code="">Unknown Result</result>
      <band id="1627">Haigh Prize</band>
      <conductor id="310730">Unknown</conductor>
    </result>
    
    <result id="185914">
      <result code="">Unknown Result</result>
      <band id="179">Haydock Band</band>
      <conductor id="310730">Unknown</conductor>
    </result>
    
    <result id="185915">
      <result code="">Unknown Result</result>
      <band id="2632">Hindley</band>
      <conductor id="310730">Unknown</conductor>
    </result>
    
    <result id="185911">
      <result code="">Unknown Result</result>
      <band id="4279">Hindley Public</band>
      <conductor id="310730">Unknown</conductor>
    </result>
    
    <result id="185913">
      <result code="">Unknown Result</result>
      <band id="1695">Horwich Old</band>
      <conductor id="310730">Unknown</conductor>
    </result>
    
    <result id="185909">
      <result code="">Unknown Result</result>
      <band id="8969">I.O.R. Bolton</band>
      <conductor id="310730">Unknown</conductor>
    </result>
    
    <result id="185907">
      <result code="">Unknown Result</result>
      <band id="2756">Leigh Silver Band</band>
      <conductor id="310730">Unknown</conductor>
    </result>
    
    <result id="185916">
      <result code="">Unknown Result</result>
      <band id="338">Matlock Band</band>
      <conductor id="310730">Unknown</conductor>
    </result>
    
    <result id="185924">
      <result code="">Unknown Result</result>
      <band id="1450">Oldham Rifles Band</band>
      <conductor id="310730">Unknown</conductor>
    </result>
    
    <result id="185923">
      <result code="">Unknown Result</result>
      <band id="4370">South Pemberton</band>
      <conductor id="310730">Unknown</conductor>
    </result>
    
    <result id="185917">
      <result code="">Unknown Result</result>
      <band id="3583">Stalybridge Borough</band>
      <conductor id="310730">Unknown</conductor>
    </result>
    
    <result id="185922">
      <result code="">Unknown Result</result>
      <band id="4371">Trafford Park Public</band>
      <conductor id="310730">Unknown</conductor>
    </result>
    
    <result id="185921">
      <result code="">Unknown Result</result>
      <band id="176">Tyldesley Band</band>
      <conductor id="310730">Unknown</conductor>
    </result>
    
    <result id="185919">
      <result code="">Unknown Result</result>
      <band id="3366">Weldbank Prize</band>
      <conductor id="310730">Unknown</conductor>
    </result>
    
    <result id="185918">
      <result code="">Unknown Result</result>
      <band id="4133">Westhoughton Old</band>
      <conductor id="310730">Unknown</conductor>
    </result>
    
  </results>
</contest-event>
