<contest-event id="17176">
  <event-date date="1881-8-6">Aug. 6, 1881<event-date>
  <event-date-resolution>D</event-date-resolution>
  <name>Great Horton Contest</name>
  <contest id="1609">
    <name>Great Horton Contest</name>
    <order>0</order>
    <contest-type id="13">Other</contest-type>
    <group id=""></group>
    <slug>great-horton-contest</slug>
    
    <notes>None</notes>
    
    
  </contest>
  
  <test-piece>
    
  </test-piece>

  <venue id="2039">Great Horton, Bradford, West Yorkshire</venue>
  <notes>6 bands entered, 5 competed

Prizes: £12, £8, £5, £3, £1</notes>

  <created>Dec. 19, 2012, 9:57 p.m.</created>
  <last-modified>Dec. 19, 2012, 9:59 p.m.</last-modified>

  <results>
    
    <result id="130398">
      <result code="1">1</result>
      <band id="2521">Heptonstall Band</band>
      <conductor id="310730">Unknown</conductor>
    </result>
    
    <result id="130399">
      <result code="2">2</result>
      <band id="126">Hebden Bridge Band</band>
      <conductor id="310730">Unknown</conductor>
    </result>
    
    <result id="130400">
      <result code="3">3</result>
      <band id="396">Littleborough Band</band>
      <conductor id="310730">Unknown</conductor>
    </result>
    
    <result id="130401">
      <result code="4">4</result>
      <band id="3726">Newchurch</band>
      <conductor id="310730">Unknown</conductor>
    </result>
    
    <result id="130402">
      <result code="5">5</result>
      <band id="3537">Rochdale Old</band>
      <conductor id="310730">Unknown</conductor>
    </result>
    
  </results>
</contest-event>
