<contest-event id="30809">
  <event-date date="1992-2-1">Feb. 1, 1992<event-date>
  <event-date-resolution>D</event-date-resolution>
  <name>CISWO Nottinghamshire (Third Section)</name>
  <contest id="3512">
    <name>CISWO Nottinghamshire (Third Section)</name>
    <order>30</order>
    <contest-type id="12">Test Piece Contest</contest-type>
    <group id="210">CISWO Nottinghamshire</group>
    <slug>ciswo-nottinghamshire-third-section</slug>
    
    <notes>None</notes>
    
    
  </contest>
  
  <test-piece>
    <test-piece id="809">Suite for Brass [Segers]</test-piece>
  </test-piece>

  <venue id="603">Nottingham, Nottinghamshire, England, UK</venue>
  <notes></notes>

  <created>Jan. 26, 2015, 4:26 p.m.</created>
  <last-modified>Jan. 26, 2015, 4:27 p.m.</last-modified>

  <results>
    
    <result id="219747">
      <result code="1">1</result>
      <band id="1490">Daw Mill Colliery Band</band>
      <conductor id="303928">Stan James</conductor>
    </result>
    
    <result id="219748">
      <result code="2">2</result>
      <band id="139">Dinnington Colliery Band</band>
      <conductor id="311045">Keith Wardle</conductor>
    </result>
    
    <result id="219749">
      <result code="3">3</result>
      <band id="881">Creswell Colliery Band</band>
      <conductor id="310787">Ken Vernon</conductor>
    </result>
    
    <result id="219750">
      <result code="4">4</result>
      <band id="2695">Heage Band</band>
      <conductor id="309872">Tom Street</conductor>
    </result>
    
  </results>
</contest-event>
