<band id="10117">
  <name>South Shields Operatic</name>
  <slug>south-shields-operatic</slug>
  <website>http://</website>
  <twitter>None</twitter>
  <region id="6">North of England</region>
  <latitude>54.999424</latitude>
  <longitude>-1.427406</longitude>
  <rehearsal>None</rehearsal>
  <rehearsal>None</rehearsal>
  
  
  <start>None</start>
  <end></end>
  <status>Extinct</status>
  <grading>None</grading>
  <scratch_band>False</scratch_band>

  <previous_names>
    
  </previous_names>
</band>
