<band id="7470">
  <name>St. Stephan Brass Band</name>
  <slug>st-stephan-brass-band</slug>
  <website>https://www.st-stephan-brassband-hamburg.de/</website>
  <twitter>None</twitter>
  <region id="23">Germany</region>
  <latitude>53.590024</latitude>
  <longitude>10.083202</longitude>
  <rehearsal>None</rehearsal>
  <rehearsal>None</rehearsal>
  
  
  <start>None</start>
  <end></end>
  <status>Competing</status>
  <grading>None</grading>
  <scratch_band>False</scratch_band>

  <previous_names>
    
    <name id="13964">St. Stephan Brass Band Hamburg</name>
    <start>None</start>
    <end>None</end>
    
  </previous_names>
</band>
