<band id="50">
  <name>Brisbane Excelsior Band</name>
  <slug>brisbane-excelsior-band</slug>
  <website>http://www.ausbrass.com/</website>
  <twitter></twitter>
  <region id="16">Australia</region>
  <latitude>-27.494977</latitude>
  <longitude>153.059002</longitude>
  <rehearsal>Tuesday</rehearsal>
  <rehearsal>None</rehearsal>
  
  
  <start>Jan. 1, 1912</start>
  <end></end>
  <status>Competing</status>
  <grading>A Grade</grading>
  <scratch_band>False</scratch_band>

  <previous_names>
    
    <name id="16969">Brisbane Brass  No.1  (Qld)</name>
    <start>None</start>
    <end>None</end>
    
    <name id="16972">Brisbane Excelsior  (Qld)</name>
    <start>None</start>
    <end>None</end>
    
    <name id="14701">E T A Concert</name>
    <start>None</start>
    <end>None</end>
    
    <name id="14697">ETA Concert</name>
    <start>None</start>
    <end>None</end>
    
  </previous_names>
</band>
