<contest-event id="22329">
  <event-date date="2012-6-16">June 16, 2012<event-date>
  <event-date-resolution>D</event-date-resolution>
  <name>Musiktage Basel (Musikpreis BB)</name>
  <contest id="4418">
    <name>Musiktage Basel (Musikpreis)</name>
    <order>0</order>
    <contest-type id="9">Own Choice Test Piece Contest</contest-type>
    <group id="427">Musiktage Basel</group>
    <slug>musiktage-basel-musikpreis-bb</slug>
    
    <notes>None</notes>
    
    
  </contest>
  
  <test-piece>
    
  </test-piece>

  <venue id="3668">Basel, Switzerland</venue>
  <notes>Best Soloist: Marc Meier, Euphonium, Brass Band Frenkendorf
Best Own Choice: Don Quixote Rhapsody, Musikverein Läufelingen
Best March: Montreal Citadel, Musikverein Buckten</notes>

  <created>July 25, 2013, 5:31 a.m.</created>
  <last-modified>May 22, 2014, 3:30 p.m.</last-modified>

  <results>
    
    <result id="166170">
      <result code="1">1</result>
      <band id="2503">Musikverein Buckten</band>
      <conductor id="308763">Roland Schaub</conductor>
      <test-piece id="2476">Purpose</test-piece>
    </result>
    
    <result id="166171">
      <result code="2">2</result>
      <band id="11130">Musikverein Läufelingen</band>
      <conductor id="298216">Marcel Bossert</conductor>
    </result>
    
    <result id="166172">
      <result code="3">3</result>
      <band id="7128">BB Frenkendorf</band>
      <conductor id="310519">Bence Toth</conductor>
      <test-piece id="1295">Diogenes</test-piece>
    </result>
    
    <result id="166173">
      <result code="4">4</result>
      <band id="9475">Musikverein Wahlen</band>
      <conductor id="299965">Manfred Cueni</conductor>
      <test-piece id="2096">Countryside and Common People</test-piece>
    </result>
    
    <result id="166174">
      <result code="5">5</result>
      <band id="7136">MV Brass Band Liesberg</band>
      <conductor id="308766">Thomas Scherrer</conductor>
      <test-piece id="1382">Adventures In Brass</test-piece>
    </result>
    
    <result id="166175">
      <result code="6">6</result>
      <band id="11171">Musikverein Eptingen</band>
      <conductor id="297618">Charles Baus</conductor>
    </result>
    
  </results>
</contest-event>
