<contest-event id="904">
  <event-date date="1995-5-13">May 13, 1995<event-date>
  <event-date-resolution>D</event-date-resolution>
  <name>Grand Shield</name>
  <contest id="16">
    <name>British Open Spring Festival (Grand Shield)</name>
    <order>10</order>
    <contest-type id="12">Test Piece Contest</contest-type>
    <group id="108">British Open Spring Festival</group>
    <slug>grand-shield</slug>
    
    <notes>Winners back to 1952 are as engraved on the current Grand Shield trophy. Except for 1981 to 1984 where the bands on the trophy appear to have come second, not first! Was a different trophy given to the winners? If you know the answer please let us know.
&lt;p&gt;
There are also results on the trophy from 1902 to 1938, but they are for the Crystal Palace Contest (see link at top of page).</notes>
    
    
  </contest>
  
  <test-piece>
    <test-piece id="42">Pageantry</test-piece>
  </test-piece>

  <venue id="26">Radisson Blu Edwardian Manchester Hotel, Manchester, Greater Manchester, England, UK</venue>
  <notes></notes>

  <created>Sept. 27, 2009, 10:34 p.m.</created>
  <last-modified>March 22, 2016, 9:11 a.m.</last-modified>

  <results>
    
    <result id="10049">
      <result code="1">1</result>
      <band id="25">Hammonds Saltaire</band>
      <conductor id="304524">David King</conductor>
    </result>
    
    <result id="10050">
      <result code="2">2</result>
      <band id="12">Whitburn Band</band>
      <conductor id="305818">Phillip McCann</conductor>
    </result>
    
    <result id="10051">
      <result code="3">3</result>
      <band id="288">Northop Band</band>
      <conductor id="312088">Thomas Wyss</conductor>
    </result>
    
    <result id="10052">
      <result code="4">4</result>
      <band id="276">Wallace Arnold (Rothwell) Band</band>
      <conductor id="306410">Alan Morrison</conductor>
    </result>
    
    <result id="10053">
      <result code="5">5</result>
      <band id="18">BTM Band</band>
      <conductor id="310035">Steve Sykes</conductor>
    </result>
    
    <result id="10054">
      <result code="6">6</result>
      <band id="13">Kirkintilloch Band</band>
      <conductor id="304381">Charles Keenan</conductor>
    </result>
    
    <result id="10055">
      <result code="7">7</result>
      <band id="233">Sovereign Brass</band>
      <conductor id="305566">David Maplestone</conductor>
    </result>
    
    <result id="10056">
      <result code="8">8</result>
      <band id="207">Stalybridge Old Band</band>
      <conductor id="302451">Trevor Halliwell</conductor>
    </result>
    
    <result id="10057">
      <result code="9">9</result>
      <band id="5">Carlton Main Frickley Colliery Band</band>
      <conductor id="300165">Jim Davies</conductor>
    </result>
    
    <result id="10058">
      <result code="10">10</result>
      <band id="277">Rhodian Brass</band>
      <conductor id="306865">Graham O&#39;Connor</conductor>
    </result>
    
    <result id="10059">
      <result code="11">11</result>
      <band id="11">Reg Vardy Band</band>
      <conductor id="303557">John Hudson</conductor>
    </result>
    
    <result id="10060">
      <result code="12">12</result>
      <band id="47">Parc and Dare Band</band>
      <conductor id="303127">John Hinckley</conductor>
    </result>
    
    <result id="10061">
      <result code="13">13</result>
      <band id="117">Ransome Band</band>
      <conductor id="303166">David Hirst</conductor>
    </result>
    
    <result id="10062">
      <result code="14">14</result>
      <band id="1204">United Norwest Co-op Rochdale Band</band>
      <conductor id="299997">Roy Curran</conductor>
    </result>
    
    <result id="10063">
      <result code="15">15</result>
      <band id="258">Point of Ayr Colliery Band</band>
      <conductor id="305566">David Maplestone</conductor>
    </result>
    
    <result id="10064">
      <result code="16">16</result>
      <band id="232">Newtongrange Band</band>
      <conductor id="298482">Derek Broadbent</conductor>
    </result>
    
    <result id="10065">
      <result code="17">17</result>
      <band id="275">John Laing (Hendon) Band</band>
      <conductor id="311837">Jeremy Wise</conductor>
    </result>
    
    <result id="10066">
      <result code="18">18</result>
      <band id="17">Redbridge Brass</band>
      <conductor id="299356">John Clark</conductor>
    </result>
    
    <result id="10067">
      <result code="19">19</result>
      <band id="118">Thoresby Colliery</band>
      <conductor id="305133">Stan Lippeatt</conductor>
    </result>
    
    <result id="10068">
      <result code="20">20</result>
      <band id="253">Stockport Brass</band>
      <conductor id="305497">John Maines</conductor>
    </result>
    
    <result id="10069">
      <result code="21">21</result>
      <band id="54">Lindley Band</band>
      <conductor id="303438">David Horsfield</conductor>
    </result>
    
    <result id="10070">
      <result code="22">22</result>
      <band id="175">Vernon Building Society (Poynton) Brass Band</band>
      <conductor id="304869">Lindsay Lawrie</conductor>
    </result>
    
  </results>
</contest-event>
