<contest-event id="38761">
  <event-date date="2017-11-18">Nov. 18, 2017<event-date>
  <event-date-resolution>D</event-date-resolution>
  <name>North Wales Rally (Youth Section A)</name>
  <contest id="1775">
    <name>North Wales Rally (Youth Section A)</name>
    <order>53</order>
    <contest-type id="9">Own Choice Test Piece Contest</contest-type>
    <group id="183">North Wales Rally</group>
    <slug>north-wales-rally-youth-section-a</slug>
    
    <notes></notes>
    
    
  </contest>
  
  <test-piece>
    
  </test-piece>

  <venue id="5647">Ysgol Brynhyfryd, Ruthin, Denbighshire, Wales, UK</venue>
  <notes></notes>

  <created>Nov. 19, 2017, 6:42 p.m.</created>
  <last-modified>Nov. 19, 2017, 6:43 p.m.</last-modified>

  <results>
    
    <result id="282025">
      <result code="1">1</result>
      <band id="2372">Beaumaris Youth</band>
      <conductor id="300993">Gwyn Evans</conductor>
      <test-piece id="1292">Olympus</test-piece>
    </result>
    
    <result id="282026">
      <result code="2">2</result>
      <band id="13646">Denbighshire Music Co-operative</band>
      <conductor id="307634">John Powell</conductor>
      <test-piece id="3427">The Journal of Phileas Fogg</test-piece>
    </result>
    
  </results>
</contest-event>
