<contest-event id="19788">
  <event-date date="1994-5-8">May 8, 1994<event-date>
  <event-date-resolution>D</event-date-resolution>
  <name>Oxfordshire &amp; District BBA Entertainment Contest (Premier Section)</name>
  <contest id="3785">
    <name>Oxfordshire &amp; District BBA Entertainment Contest (Upper Sections)</name>
    <order>10</order>
    <contest-type id="2">Entertainments Contest</contest-type>
    <group id="100">Oxfordshire &amp; District BBA Entertainment Contest</group>
    <slug>oxfordshire-district-brass-band-associat-3785</slug>
    
    <notes>None</notes>
    
    
  </contest>
  
  <test-piece>
    
  </test-piece>

  <venue id="3349">Cowley Workers&#39; Social Club, Oxford</venue>
  <notes>In this first year of running the new &#39;Premier&#39; section, it was combined with the &#39;A&#39; section, which only had 2 entries.

Best Instrumentalist: Ian Wright, Euphonium, Unity Brass (&#39;Meditation from Thais&#39;)
Best Section A Band: East Woodhay

Presentation:
1 Wantage A, 86
2= Morrells Kidlington, 84
2= Brackley &amp; District,84
4= Shipston Town, 83
4= East Woodhay, 83
4= Kennington, 83
7 Unity, 80

Best Percussionist of the Day: Morrells Kidlington
Best Tenor Horn of the Day: Morrells Kidlington</notes>

  <created>March 26, 2013, 11:48 p.m.</created>
  <last-modified>Sept. 26, 2015, 12:25 p.m.</last-modified>

  <results>
    
    <result id="148044">
      <result code="1">1</result>
      <band id="295">Kidlington Concert Brass</band>
      <conductor id="310724">Catherine Underwood</conductor>
    </result>
    
    <result id="148045">
      <result code="2">2</result>
      <band id="479">Oddfellows Brass</band>
      <conductor id="298239">Robert Boulter</conductor>
    </result>
    
    <result id="148046">
      <result code="3">3</result>
      <band id="472">Brackley and District Band</band>
      <conductor id="297795">John Bennett</conductor>
    </result>
    
    <result id="148047">
      <result code="4">4</result>
      <band id="414">Wantage Silver Band</band>
      <conductor id="311829">John Winterflood</conductor>
    </result>
    
    <result id="148048">
      <result code="5">5</result>
      <band id="509">Shipston Town Band</band>
      <conductor id="312099">Les Yarrow</conductor>
    </result>
    
    <result id="148049">
      <result code="6">6</result>
      <band id="1481">East Woodhay Silver</band>
      <conductor id="298609">James Brown</conductor>
    </result>
    
    <result id="148050">
      <result code="7">7</result>
      <band id="1968">Kennington (Oxford)</band>
      <conductor id="309924">Ron Sudworth</conductor>
    </result>
    
  </results>
</contest-event>
