<contest-event id="28627">
  <event-date date="1982-3-6">March 6, 1982<event-date>
  <event-date-resolution>D</event-date-resolution>
  <name>Cornwall BBA Contest (Youth Section)</name>
  <contest id="3211">
    <name>Cornwall BBA Contest (Youth Section)</name>
    <order>0</order>
    <contest-type id="12">Test Piece Contest</contest-type>
    <group id="74">Cornwall Brass Band Association Contest</group>
    <slug>cornwall-bba-contest-youth-section</slug>
    
    <notes>None</notes>
    
    
  </contest>
  
  <test-piece>
    <test-piece id="553">Voices of Youth</test-piece>
  </test-piece>

  <venue id="3178">City Hall, Truro, Cornwall, England, UK</venue>
  <notes></notes>

  <created>June 18, 2014, 11:38 a.m.</created>
  <last-modified>June 18, 2014, 11:38 a.m.</last-modified>

  <results>
    
    <result id="204563">
      <result code="1">1</result>
      <band id="1778">St. Dennis Youth</band>
      <conductor id="311611">Eddie Williams</conductor>
    </result>
    
    <result id="204564">
      <result code="2">2</result>
      <band id="1451">Camborne Junior Contesting</band>
      <conductor id="302166">Derek Greenwood</conductor>
    </result>
    
    <result id="204565">
      <result code="3">3</result>
      <band id="1780">St. Austell Youth</band>
      <conductor id="308133">Rodney Richards</conductor>
    </result>
    
  </results>
</contest-event>
