<contest-event id="25001">
  <event-date date="1934-7-14">July 14, 1934<event-date>
  <event-date-resolution>D</event-date-resolution>
  <name>Fairford Contest (Section 1)</name>
  <contest id="3937">
    <name>Fairford Contest (Section 1)</name>
    <order>10</order>
    <contest-type id="12">Test Piece Contest</contest-type>
    <group id="398">Fairford Contest</group>
    <slug>fairford-contest-section-1</slug>
    
    <notes>None</notes>
    
    
  </contest>
  <contest-type-override id="12">Test Piece Contest</contest-type-override>
  <test-piece>
    <test-piece id="1385">The White Rider</test-piece>
  </test-piece>

  <venue id="1210">Fairford, Gloucestershire, England, UK</venue>
  <notes>6 bands competed.

Prizes: £25, £15, £10</notes>

  <created>Nov. 8, 2013, 9:58 a.m.</created>
  <last-modified>Jan. 22, 2014, 1:59 p.m.</last-modified>

  <results>
    
    <result id="182144">
      <result code="1">1</result>
      <band id="408">Hanwell Band</band>
      <conductor id="300686">Joseph Crawford Dyson</conductor>
    </result>
    
    <result id="182145">
      <result code="2">2</result>
      <band id="276">Wallace Arnold (Rothwell) Band</band>
      <conductor id="306836">Harry Nuttall</conductor>
    </result>
    
    <result id="182146">
      <result code="3">3</result>
      <band id="6460">Friary Brewery</band>
      <conductor id="312039">Denis Wright</conductor>
    </result>
    
    <result id="182147">
      <result code="">Unknown Result</result>
      <band id="1640">Callenders Cableworks Band</band>
      <conductor id="310730">Unknown</conductor>
    </result>
    
    <result id="182149">
      <result code="">Unknown Result</result>
      <band id="3340">Kingswood Evangel</band>
      <conductor id="310730">Unknown</conductor>
    </result>
    
    <result id="182148">
      <result code="">Unknown Result</result>
      <band id="4448">Kirby Imperial</band>
      <conductor id="310730">Unknown</conductor>
    </result>
    
  </results>
</contest-event>
