<contest-event id="40953">
  <event-date date="1924-4-26">April 26, 1924<event-date>
  <event-date-resolution>D</event-date-resolution>
  <name>Glazebury Contest</name>
  <contest id="4539">
    <name>Glazebury Contest</name>
    <order>0</order>
    <contest-type id="12">Test Piece Contest</contest-type>
    <group id=""></group>
    <slug>glazebury-contest</slug>
    
    <notes>None</notes>
    
    
  </contest>
  
  <test-piece>
    <test-piece id="781">Gems of Italian Opera</test-piece>
  </test-piece>

  <venue id="3925">Glazebury, Lancashire</venue>
  <notes>Prizes - 1st £20 and cup, 2nd £10, 3rd £5, 4th £3, 5th £2.
10 bands competed.</notes>

  <created>Oct. 25, 2018, 8:42 p.m.</created>
  <last-modified>Oct. 25, 2018, 9:35 p.m.</last-modified>

  <results>
    
    <result id="297360">
      <result code="1">1</result>
      <band id="1447">Blackburn&#39;s Steel Works Band</band>
      <conductor id="310730">Unknown</conductor>
    </result>
    
    <result id="297361">
      <result code="2">2</result>
      <band id="1653">Pendleton Public</band>
      <conductor id="310730">Unknown</conductor>
    </result>
    
    <result id="297362">
      <result code="3">3</result>
      <band id="2757">Milnrow Public Band</band>
      <conductor id="310730">Unknown</conductor>
    </result>
    
    <result id="297363">
      <result code="4">4</result>
      <band id="1652">Nutgrove</band>
      <conductor id="310730">Unknown</conductor>
    </result>
    
    <result id="297364">
      <result code="5">5</result>
      <band id="17325">Tyldesley Wesleyan Temperance</band>
      <conductor id="310730">Unknown</conductor>
    </result>
    
  </results>
</contest-event>
