<band id="652">
  <name>MacTaggart Scott Loanhead</name>
  <slug>mactaggart-scott-loanhead</slug>
  <website>http://www.loanheadbrass.org.uk/</website>
  <twitter></twitter>
  <region id="7">Scotland</region>
  <latitude>55.881257</latitude>
  <longitude>-3.152304</longitude>
  <rehearsal>Monday</rehearsal>
  <rehearsal>None</rehearsal>
  <parent id="7952">Loanhead Burgh</parent>
  
  <start>Jan. 1, 1943</start>
  <end></end>
  <status>Competing</status>
  <grading>Fourth</grading>
  <scratch_band>False</scratch_band>

  <previous_names>
    
    <name id="666">MacTaggart Scott Loanhead Silver</name>
    <start>None</start>
    <end>None</end>
    
    <name id="910">MacTaggart Scott Silver Loanhead</name>
    <start>None</start>
    <end>None</end>
    
    <name id="5364">MacTaggart Scott Works Silver</name>
    <start>None</start>
    <end>None</end>
    
    <name id="913">McTaggart Scott</name>
    <start>None</start>
    <end>None</end>
    
    <name id="7574">McTaggart Scott Loanhead Band</name>
    <start>None</start>
    <end>None</end>
    
  </previous_names>
</band>
