<band id="4075">
  <name>Mickley Collery Workmen&#39;s</name>
  <slug>mickley-collery-workmen-s</slug>
  <website>http://</website>
  <twitter></twitter>
  <region id="6">North of England</region>
  <latitude>54.953618</latitude>
  <longitude>-1.883726</longitude>
  <rehearsal>None</rehearsal>
  <rehearsal>None</rehearsal>
  
  
  <start>None</start>
  <end></end>
  <status>Extinct</status>
  <grading>None</grading>
  <scratch_band>False</scratch_band>

  <previous_names>
    
    <name id="10503">Mickley Colliery</name>
    <start>None</start>
    <end>None</end>
    
  </previous_names>
</band>
