<contest-event id="9155">
  <event-date date="1884-9-15">Sept. 15, 1884<event-date>
  <event-date-resolution>D</event-date-resolution>
  <name>Matlock Contest</name>
  <contest id="1205">
    <name>Matlock Contest</name>
    <order>0</order>
    <contest-type id="12">Test Piece Contest</contest-type>
    <group id=""></group>
    <slug>matlock-contest</slug>
    
    <notes>None</notes>
    
    
  </contest>
  <contest-type-override id="9">Own Choice Test Piece Contest</contest-type-override>
  <test-piece>
    
  </test-piece>

  <venue id="1097">Old English Hotel, Matlock Bridge</venue>
  <notes>Contest for Derbyshire Bands only.</notes>

  <created>Dec. 21, 2011, 8:51 p.m.</created>
  <last-modified>July 22, 2018, 2:56 p.m.</last-modified>

  <results>
    
    <result id="79315">
      <result code="1">1</result>
      <band id="6213">Chesterfield and Hasland</band>
      <conductor id="306482">W. Mountney</conductor>
      <test-piece id="1675">Atilla [arr. Round]</test-piece>
    </result>
    
    <result id="79312">
      <result code="2">2</result>
      <band id="5896">Staveley Volunteers</band>
      <conductor id="306838">J. Nuttall</conductor>
      <test-piece id="1820">Leisure Times</test-piece>
    </result>
    
    <result id="79316">
      <result code="3">3</result>
      <band id="3524">Derby United</band>
      <conductor id="308870">Alfred R. Seddon</conductor>
      <test-piece id="967">Magic Flute [unknown arranger]</test-piece>
    </result>
    
    <result id="79310">
      <result code="4">4</result>
      <band id="4775">Belper Band</band>
      <conductor id="309291">J. C. Smallwood</conductor>
      <test-piece id="2195">Reminiscences of Donizetti [arr. Smith]</test-piece>
    </result>
    
    <result id="79313">
      <result code="5">5</result>
      <band id="5209">Codnor United</band>
      <conductor id="306616">John Naylor</conductor>
      <test-piece id="1912">Les Huguenots [unknown arranger]</test-piece>
    </result>
    
    <result id="79311">
      <result code="">Unknown Result</result>
      <band id="6225">Birchover</band>
      <conductor id="301567">James Frost</conductor>
      <test-piece id="1455">Kyrie and Gloria from Mozart&#39;s 12th Mass [unknown arranger]</test-piece>
    </result>
    
    <result id="79308">
      <result code="">Unknown Result</result>
      <band id="4591">Hayfield</band>
      <conductor id="310006">Edwin Swift</conductor>
      <test-piece id="1207">Semiramide [unknown arranger]</test-piece>
    </result>
    
    <result id="79309">
      <result code="">Unknown Result</result>
      <band id="5208">Heanor Church Temperance</band>
      <conductor id="307990">A. S. Redgate</conductor>
      <test-piece id="1226">Operatic Selection [unknown arranger]</test-piece>
    </result>
    
    <result id="79314">
      <result code="">Unknown Result</result>
      <band id="6090">Long Eaton Temperance Band</band>
      <conductor id="310833">E. Voce</conductor>
      <test-piece id="2271">Iolanthe (selection)</test-piece>
    </result>
    
    <result id="79317">
      <result code="W">Withdrawn</result>
      <band id="3493">Clay Cross</band>
      <conductor id="310730">Unknown</conductor>
    </result>
    
    <result id="79318">
      <result code="W">Withdrawn</result>
      <band id="1863">New Mills Band</band>
      <conductor id="310730">Unknown</conductor>
    </result>
    
  </results>
</contest-event>
