<contest-event id="32685">
  <event-date date="2016-4-1">April 1, 2016<event-date>
  <event-date-resolution>D</event-date-resolution>
  <name>Gouden Spiker Festival (Fifth Division)</name>
  <contest id="5663">
    <name>Gouden Spiker Festival (Fifth Division)</name>
    <order>50</order>
    <contest-type id="11">Set Test and Own Choice</contest-type>
    <group id="552">Gouden Spiker Festival</group>
    <slug>gouden-spiker-festival-netherlands-5th-division</slug>
    
    <notes>None</notes>
    
    
  </contest>
  
  <test-piece>
    <test-piece id="3465">Epic Journey</test-piece>
  </test-piece>

  <venue id="5813">De Wier, Ureterp, Friesland, Netherlands</venue>
  <notes>Set Work:
1. Pro Rege B - Heerenveen o.l.v. Martine Reijenga
2. Euphonia - Wolvega o.l.v. Froukje Hoekstra
3. De Eendracht - Marrum o.l.v. Johan Hager

Soloists:
1. Jonathan Henneveld (Bas trombone) - Pro Rege B Heerenveen
2. Robin Heslinga (Cornet) - Euphonia Wolvega
3. Willem Adema, Jan Berend Dijkstra, Marcel Terpstra (Trombones) - De Eendracht Marrum</notes>

  <created>Sept. 11, 2015, 11:46 a.m.</created>
  <last-modified>May 6, 2017, 12:34 p.m.</last-modified>

  <results>
    
    <result id="248687">
      <result code="1">1</result>
      <band id="12454">Brass Band Pro Rege B</band>
      <conductor id="308046">Martine Reijenga</conductor>
    </result>
    
    <result id="248688">
      <result code="2">2</result>
      <band id="13292">Brassband Euphonia Wolvega &#39;B&#39;</band>
      <conductor id="303230">Froukje Hoekstra</conductor>
    </result>
    
    <result id="236198">
      <result code="3">3</result>
      <band id="12786">Eendracht Marrum</band>
      <conductor id="302366">Johan Hager</conductor>
    </result>
    
  </results>
</contest-event>
