<contest-event id="25063">
  <event-date date="1936-5-15">May 15, 1936<event-date>
  <event-date-resolution>D</event-date-resolution>
  <name>Liverpool Catholic Contest</name>
  <contest id="4823">
    <name>Liverpool Catholic Contest</name>
    <order>0</order>
    <contest-type id="13">Other</contest-type>
    <group id=""></group>
    <slug>liverpool-catholic-contest</slug>
    
    <notes>None</notes>
    
    
  </contest>
  
  <test-piece>
    
  </test-piece>

  <venue id="4226">St Patrick&#39;s Hall, Liverpool</venue>
  <notes>
  4 bands competed.</notes>

  <created>Nov. 12, 2013, 9:16 a.m.</created>
  <last-modified>Nov. 12, 2013, 9:22 a.m.</last-modified>

  <results>
    
    <result id="182570">
      <result code="1">1</result>
      <band id="5321">Warrington Catholic</band>
      <conductor id="305179">F. V. Lloyd</conductor>
    </result>
    
    <result id="182573">
      <result code="">Unknown Result</result>
      <band id="10013">Nazareth House (Ditton)</band>
      <conductor id="310730">Unknown</conductor>
    </result>
    
    <result id="182572">
      <result code="">Unknown Result</result>
      <band id="11639">St Francis de Sales</band>
      <conductor id="310730">Unknown</conductor>
    </result>
    
    <result id="182571">
      <result code="">Unknown Result</result>
      <band id="5378">St. Vincents de Paul</band>
      <conductor id="310730">Unknown</conductor>
    </result>
    
  </results>
</contest-event>
